Metadata-Version: 2.4
Name: mseep-mcp-server
Version: 0.4.4
Summary: Add your description here
Author-email: mseep <support@skydeck.ai>
Requires-Python: >=3.11
Requires-Dist: bs4>=0.0.2
Requires-Dist: httpx>=0.28.1
Requires-Dist: mcp[cli]>=1.4.1
Requires-Dist: openai>=1.66.3
